{
  "interview_id": "interview_002_20250913_175031",
  "timestamp": "2025-09-13T17:53:12.216531",
  "total_questions": 13,
  "analyses": [
    {
      "question_number": 1,
      "question": "به نظرتون مهم‌ترین رنج یا چیزی که دارید راجع بهش فکر می‌کنید در این سن چیست؟",
      "answer": "یکی از مشکلات، گرانی است. خیلی گرونیه. الان دقدقه من اینه که پسر مجرد دارم و دقدقه جوان‌ها رو بیشتر دارم. مشکل زندگی زیاده. خیلی از این بابت نگرانم.",
      "analysis": {
        "unhealthy": [
          {
            "aspect": "emotion",
            "subject": "اضطراب و تشویش",
            "based_on_answer": "خیلی از این بابت نگرانم.",
            "reasoning": "نگرانی زیاد نسبت به مشکلات زندگی و دغدغه جوان‌ها نشان‌دهنده اضطراب و تشویش است که می‌تواند منجر به عدم آرامش روانی شود."
          },
          {
            "aspect": "belief",
            "subject": "نگرش منفی و سیاهنمایی نسبت به شرایط اقتصادی",
            "based_on_answer": "یکی از مشکلات، گرانی است. خیلی گرونیه.",
            "reasoning": "تمرکز بر گرانی و مشکلات اقتصادی می‌تواند نشان‌دهنده نگرش منفی نسبت به شرایط باشد که ممکن است بر سلامت روان تأثیر بگذارد."
          },
          {
            "aspect": "behavior",
            "subject": "انفعال و وابستگی به سبک قدیم",
            "based_on_answer": "مشکل زندگی زیاده.",
            "reasoning": "بیان مشکلات بدون اشاره به راه‌حل یا اقدام مثبت برای مقابله با آن‌ها ممکن است نشان‌دهنده انفعال در رفتار باشد."
          }
        ],
        "healthy": [
          {
            "aspect": "emotion",
            "subject": "دغدغه‌مندی نسبت به دیگران",
            "based_on_answer": "الان دقدقه من اینه که پسر مجرد دارم و دقدقه جوان‌ها رو بیشتر دارم.",
            "reasoning": "ابراز نگرانی و توجه به مشکلات جوانان نشان‌دهنده احساس مسئولیت و همدلی نسبت به دیگران است که جنبه‌ای مثبت از سلامت روان می‌باشد."
          },
          {
            "aspect": "belief",
            "subject": "احسان مداری ارتباطی",
            "based_on_answer": "الان دقدقه من اینه که پسر مجرد دارم و دقدقه جوان‌ها رو بیشتر دارم.",
            "reasoning": "نگاه مشفقانه و دغدغه‌مند نسبت به جوانان می‌تواند نشان‌دهنده نگرش مثبت و احسان مداری در ارتباطات باشد."
          }
        ]
      }
    },
    {
      "question_number": 2,
      "question": "مشکلی روحی یا جسمانی بیشتر از سایر مشکلات احساس می‌کنید؟",
      "answer": "نه، من خودم را خیلی از این بابت نمی‌بینم. بابت گرانی و مشکلات زندگی نگرانم.",
      "analysis": {
        "unhealthy": [
          {
            "aspect": "emotion",
            "subject": "اضطراب و تشویش",
            "based_on_answer": "بابت گرانی و مشکلات زندگی نگرانم.",
            "reasoning": "نگرانی در مورد مسائل اقتصادی و مشکلات زندگی می‌تواند نشانه‌ای از اضطراب یا تشویش باشد. این وضعیت ممکن است به مرور زمان بر سلامت روان فرد اثر منفی بگذارد و نیاز به مدیریت بهتر داشته باشد."
          }
        ],
        "healthy": [
          {
            "aspect": "belief",
            "subject": "پذیرندگی",
            "based_on_answer": "نه، من خودم را خیلی از این بابت نمی‌بینم.",
            "reasoning": "پذیرش این موضوع که فرد مشکلی روحی یا جسمانی خاصی ندارد، نشان‌دهنده پذیرندگی و توانایی تطبیق سالم با شرایط موجود است. این نگرش می‌تواند به حفظ سلامت روان کمک کند."
          },
          {
            "aspect": "belief",
            "subject": "توسعه معنای دارایی",
            "based_on_answer": "بابت گرانی و مشکلات زندگی نگرانم.",
            "reasoning": "نگرانی در مورد گرانی نشان می‌دهد که فرد به مسائل مادی اهمیت می‌دهد. اگر این نگرانی به سمت توسعه معنای دارایی هدایت شود، می‌تواند به دیدگاه مثبت‌تر و سالم‌تر در مورد زندگی منجر شود."
          },
          {
            "aspect": "behavior",
            "subject": "قناعت ورزی",
            "based_on_answer": "نه، من خودم را خیلی از این بابت نمی‌بینم.",
            "reasoning": "عدم ابراز مشکلات روحی یا جسمانی ممکن است نشان‌دهنده قناعت‌ورزی و توانایی فرد در مدیریت نیازها و انتظارات باشد که به عنوان یک رفتار مثبت تلقی می‌شود."
          }
        ]
      }
    },
    {
      "question_number": 3,
      "question": "به نظر شما منشا این مشکلات کجاست؟",
      "answer": "از همین حکومت و سیاست‌هاست. هیچ نظارتی وجود نداره و ما در این مشکلات دست و پنجه نرم می‌کنیم.",
      "analysis": {
        "unhealthy": [
          {
            "aspect": "emotion",
            "subject": "ناامیدی",
            "based_on_answer": "هیچ نظارتی وجود نداره و ما در این مشکلات دست و پنجه نرم می‌کنیم.",
            "reasoning": "ناامیدی به وضوح در لحن و محتوای پاسخ کاربر قابل مشاهده است. بیان مشکلات بدون ارائه راه‌حل یا امید به بهبود، نشان‌دهنده وجود هیجان منفی پایدار است."
          },
          {
            "aspect": "belief",
            "subject": "نگرش منفی و سیاهنمایی نسبت به سابقه شغلی یا اجتماعی",
            "based_on_answer": "از همین حکومت و سیاست‌هاست.",
            "reasoning": "کاربر در پاسخ خود به طور کامل مشکلات را به حکومت و سیاست‌ها نسبت می‌دهد و به طور کلی دیدگاه منفی و بدون سازندگی نسبت به شرایط اجتماعی ارائه می‌دهد."
          },
          {
            "aspect": "emotion",
            "subject": "نارضایتی",
            "based_on_answer": "هیچ نظارتی وجود نداره و ما در این مشکلات دست و پنجه نرم می‌کنیم.",
            "reasoning": "کاربر نارضایتی خود را از شرایط موجود به طور مستقیم بیان کرده است که این موضوع نشان‌دهنده یک هیجان منفی پایدار است."
          }
        ],
        "healthy": []
      }
    },
    {
      "question_number": 4,
      "question": "آیا خودتان برای حل این مشکلات چه کار کردید؟",
      "answer": "من خیلی از خودم می‌زنم. کمتر خرید می‌کنم، از لباس پوشیدنم کم می‌کنم و زیبایی‌های زندگی‌ام را نادیده می‌گیرم.",
      "analysis": {
        "unhealthy": [
          {
            "aspect": "emotion",
            "subject": "ناامیدی",
            "based_on_answer": "من خیلی از خودم می‌زنم.",
            "reasoning": "این جمله نشان‌دهنده احساس ناامیدی و نارضایتی است که ممکن است به دلیل فشارهای مالی یا روانی به وجود آمده باشد. از منظر روانشناسی، این احساسات می‌توانند به کاهش تاب‌آوری و افزایش اضطراب منجر شوند."
          },
          {
            "aspect": "behavior",
            "subject": "عدم روزآمدسازی روش‌های درآمدزایی",
            "based_on_answer": "کمتر خرید می‌کنم، از لباس پوشیدنم کم می‌کنم و زیبایی‌های زندگی‌ام را نادیده می‌گیرم.",
            "reasoning": "این رفتار نشان‌دهنده انفعال و عدم تلاش برای تغییر سبک زندگی یا پیدا کردن راه‌های جدید برای حل مشکلات مالی است. چنین رفتارهایی می‌توانند به رکود رشدی و کاهش انگیزه سالمند منجر شوند."
          },
          {
            "aspect": "belief",
            "subject": "بی معنایی زندگی",
            "based_on_answer": "زیبایی‌های زندگی‌ام را نادیده می‌گیرم.",
            "reasoning": "نادیده گرفتن زیبایی‌های زندگی نشان‌دهنده نگرش منفی و سیاه‌نمایی نسبت به زندگی است که می‌تواند به احساس بی‌معنایی و کاهش کیفیت زندگی منجر شود."
          }
        ],
        "healthy": [
          {
            "aspect": "behavior",
            "subject": "قناعت ورزی",
            "based_on_answer": "کمتر خرید می‌کنم، از لباس پوشیدنم کم می‌کنم.",
            "reasoning": "این رفتار نشان‌دهنده تلاش برای مدیریت منابع و کاهش هزینه‌ها در شرایط دشوار است. قناعت ورزی می‌تواند در برخی شرایط به حفظ ثبات مالی و کاهش استرس کمک کند."
          }
        ]
      }
    },
    {
      "question_number": 5,
      "question": "نادیده گرفتن نیازهای خود، چقدر بر روی روحیه‌تان اثر دارد؟",
      "answer": "بله، احساس خوبی ندارم. استرس دارم و ناغمگین هستم. دارو می‌خورم.",
      "analysis": {
        "unhealthy": [
          {
            "aspect": "emotion",
            "subject": "ناامیدی",
            "based_on_answer": "احساس خوبی ندارم.",
            "reasoning": "عبارت 'احساس خوبی ندارم' نشان‌دهنده عدم رضایت و ناامیدی است. ناامیدی به‌عنوان یک هیجان منفی پایدار می‌تواند بر سلامت روان تأثیر منفی بگذارد و نیازمند بررسی و مداخله است."
          },
          {
            "aspect": "emotion",
            "subject": "اضطراب و تشویش",
            "based_on_answer": "استرس دارم.",
            "reasoning": "استرس یک هیجان منفی است که می‌تواند به اضطراب و تشویش منجر شود. این وضعیت ممکن است ناشی از عدم توانایی در مدیریت هیجانات یا فشارهای محیطی باشد."
          },
          {
            "aspect": "emotion",
            "subject": "اندوه",
            "based_on_answer": "ناغمگین هستم.",
            "reasoning": "اندوه و ناراحتی پایدار می‌تواند نشان‌دهنده مشکلات عاطفی عمیق‌تر باشد که نیازمند بررسی و مداخله است."
          },
          {
            "aspect": "behavior",
            "subject": "خود آرامسازی ناسالم",
            "based_on_answer": "دارو می‌خورم.",
            "reasoning": "استفاده از دارو به‌عنوان تنها راه‌حل ممکن است به معنای اتکای ناسالم به دارو برای مدیریت هیجانات باشد. این رفتار نیازمند بررسی بیشتر برای شناسایی دلایل ریشه‌ای و ارائه راه‌حل‌های جایگزین است."
          }
        ],
        "healthy": []
      }
    },
    {
      "question_number": 6,
      "question": "داروها کمکی به شما کرده‌اند؟",
      "answer": "بله، تا حد زیادی کمک کرده‌اند.",
      "analysis": {
        "unhealthy": [],
        "healthy": [
          {
            "aspect": "emotion",
            "subject": "پذیرندگی",
            "based_on_answer": "بله، تا حد زیادی کمک کرده‌اند.",
            "reasoning": "پذیرش بهبودی ناشی از مصرف داروها نشان‌دهنده سلامت هیجانی است، زیرا فرد تغییرات مثبت در شرایط خود را پذیرفته و نسبت به آن امیدواری نشان داده است."
          },
          {
            "aspect": "belief",
            "subject": "باورمندی به قاعده سبب و مسبب",
            "based_on_answer": "بله، تا حد زیادی کمک کرده‌اند.",
            "reasoning": "پاسخ نشان‌دهنده این باور است که داروها به عنوان یک علت بهبود شرایط جسمی و روانی فرد عمل کرده‌اند. این نوع نگرش منطقی به علت و معلول نشان‌دهنده سلامت باور فرد است."
          },
          {
            "aspect": "behavior",
            "subject": "خود مراقبتی",
            "based_on_answer": "بله، تا حد زیادی کمک کرده‌اند.",
            "reasoning": "استفاده از داروها و ابراز رضایت از تأثیر آنها نشان‌دهنده رفتار مسئولانه در مراقبت از خود و توجه به نیازهای جسمی و روانی است."
          }
        ]
      }
    },
    {
      "question_number": 7,
      "question": "آیا در زمینه سلامت جسمانی هم مشکلاتی دارید؟",
      "answer": "بله، به ویژه مشکلات حرکتی و درد مفاصل. هم مشکل جسمانی و هم روحی دارم.",
      "analysis": {
        "unhealthy": [
          {
            "aspect": "emotion",
            "subject": "ناامیدی",
            "based_on_answer": "هم مشکل جسمانی و هم روحی دارم.",
            "reasoning": "بیان اینکه فرد علاوه بر مشکلات جسمانی، مشکلات روحی نیز دارد، می‌تواند نشان‌دهنده وجود احساس ناامیدی یا نارضایتی باشد که ممکن است از تجربه دردهای جسمانی و تأثیر آن بر زندگی روزمره ناشی شده باشد."
          },
          {
            "aspect": "belief",
            "subject": "تصویر بدنی نازیبا و بی ارزش از سالمندی خود داشتن",
            "based_on_answer": "مشکلات حرکتی و درد مفاصل.",
            "reasoning": "اشاره به مشکلات جسمی و حرکتی می‌تواند نشان‌دهنده باور ناسالم نسبت به کاهش توانایی‌های جسمانی باشد که ممکن است بر تصویر ذهنی فرد از خود تأثیر منفی بگذارد."
          }
        ],
        "healthy": [
          {
            "aspect": "emotion",
            "subject": "پذیرندگی",
            "based_on_answer": "بله، به ویژه مشکلات حرکتی و درد مفاصل.",
            "reasoning": "بیان مشکلات جسمانی با پذیرش و بدون اشاره به نارضایتی شدید یا شکایت مداوم، نشان‌دهنده پذیرندگی سالم نسبت به تغییرات طبیعی جسمی در دوران سالمندی است."
          },
          {
            "aspect": "behavior",
            "subject": "خود مراقبتی",
            "based_on_answer": "مشکلات حرکتی و درد مفاصل.",
            "reasoning": "اشاره به مشکلات جسمی می‌تواند نشان‌دهنده آگاهی فرد نسبت به وضعیت جسمانی خود باشد و اگر با پیگیری درمان یا اقدام برای بهبود وضعیت همراه باشد، نشان‌دهنده رفتار خود مراقبتی است."
          }
        ]
      }
    },
    {
      "question_number": 8,
      "question": "آیا بیماری‌هایی در خانوادتان بوده که بر روی شما تأثیر گذاشته باشد؟",
      "answer": "بله، برادرم که شهید شد و مریضی‌های دیگر در خانواده باعث ناراحتی من شده.",
      "analysis": {
        "unhealthy": [
          {
            "aspect": "emotion",
            "subject": "پایداری هیجانات منفی - اندوه",
            "based_on_answer": "مریضی‌های دیگر در خانواده باعث ناراحتی من شده.",
            "reasoning": "این جمله نشان‌دهنده اندوه و ناراحتی عمیقی است که فرد از بیماری‌ها و فقدان در خانواده تجربه کرده است. این نوع احساسات اگر پایدار بمانند و به درستی پردازش نشوند، می‌توانند سلامت روان را تحت تأثیر قرار دهند."
          },
          {
            "aspect": "emotion",
            "subject": "پایداری هیجانات منفی - بی‌تابی",
            "based_on_answer": "برادرم که شهید شد و مریضی‌های دیگر در خانواده باعث ناراحتی من شده.",
            "reasoning": "فقدان برادر و بیماری‌های خانواده به نظر می‌رسد که باعث نوعی بی‌تابی در فرد شده است. این وضعیت می‌تواند نشان‌دهنده عدم پذیرش کامل این اتفاقات باشد که ممکن است بر سلامت روان تأثیر منفی بگذارد."
          }
        ],
        "healthy": [
          {
            "aspect": "belief",
            "subject": "رحلت نگری بیدارگرانه",
            "based_on_answer": "برادرم که شهید شد",
            "reasoning": "اشاره به شهادت برادر می‌تواند نشان‌دهنده این باشد که فرد به نوعی معنای والاتر یا روحانی برای مرگ قائل است، که می‌تواند به کاهش اضطراب و اندوه ناشی از فقدان کمک کند."
          },
          {
            "aspect": "emotion",
            "subject": "پذیرندگی",
            "based_on_answer": "مریضی‌های دیگر در خانواده باعث ناراحتی من شده.",
            "reasoning": "اگرچه فرد ناراحتی را تجربه کرده است، اما به نظر می‌رسد که توانسته این احساسات را شناسایی کرده و به نوعی بپذیرد. پذیرش این احساسات اولین گام در مسیر سازگاری و سلامت روان است."
          }
        ]
      }
    },
    {
      "question_number": 9,
      "question": "فقدان آن‌هایی که دوست داشتید چه حسی برایتان به همراه آورده است؟",
      "answer": "خیلی سخت است. بعد از دست دادن آن‌ها دیگر زندگی برایم جذاب نیست.",
      "analysis": {
        "unhealthy": [
          {
            "aspect": "emotion",
            "subject": "ناامیدی",
            "based_on_answer": "بعد از دست دادن آن‌ها دیگر زندگی برایم جذاب نیست.",
            "reasoning": "عبارت 'دیگر زندگی برایم جذاب نیست' نشان‌دهنده احساس ناامیدی در فرد است. این احساس می‌تواند نتیجه از دست دادن عزیزان باشد و به عنوان هیجانی ناسالم، پایداری آن می‌تواند باعث کاهش کیفیت زندگی فرد شود."
          },
          {
            "aspect": "belief",
            "subject": "بی معنایی زندگی",
            "based_on_answer": "بعد از دست دادن آن‌ها دیگر زندگی برایم جذاب نیست.",
            "reasoning": "عبارت مذکور حاکی از باور به بی‌معنایی زندگی پس از فقدان عزیزان است. این نشانگر ناسالم می‌تواند ناشی از عدم بازتعریف معنای زندگی یا ناتوانی در پذیرش شرایط جدید باشد."
          }
        ],
        "healthy": []
      }
    },
    {
      "question_number": 10,
      "question": "آیا امیدی برای آینده دارید؟",
      "answer": "همیشه امیدوارم ولی مشکلات زندگی بسیار زیاد است و به شدت فشار می‌آورد.",
      "analysis": {
        "unhealthy": [
          {
            "aspect": "emotion",
            "subject": "احساس فشار و اضطراب",
            "based_on_answer": "مشکلات زندگی بسیار زیاد است و به شدت فشار می‌آورد.",
            "reasoning": "بیان احساس فشار زیاد نشان‌دهنده وجود هیجانات منفی و اضطراب است که ممکن است به سلامت روان فرد آسیب برساند. این احساس می‌تواند ناشی از استرس‌های مداوم یا عدم توانایی در مدیریت مشکلات باشد."
          }
        ],
        "healthy": [
          {
            "aspect": "emotion",
            "subject": "امیدواری",
            "based_on_answer": "همیشه امیدوارم",
            "reasoning": "وجود امیدواری نشان‌دهنده پایداری هیجانات مثبت است که به عنوان یک عامل محافظتی در برابر استرس و ناامیدی عمل می‌کند. این هیجان مثبت می‌تواند به فرد کمک کند تا با مشکلات بهتر مقابله کند."
          }
        ]
      }
    },
    {
      "question_number": 11,
      "question": "آیا افرادی مثل فرزندان‌تان شما را در این دوران حمایت می‌کنند؟",
      "answer": "بله، دو دختری دارم که حمایت می‌کنند و امیدوارم که زندگی بهتری برای آن‌ها فراهم کنم.",
      "analysis": {
        "unhealthy": [],
        "healthy": [
          {
            "aspect": "behavior",
            "subject": "خدمت پذیری",
            "based_on_answer": "بله، دو دختری دارم که حمایت می‌کنند",
            "reasoning": "پذیرش حمایت از دیگران، به‌ویژه از فرزندان، نشان‌دهنده توانایی سالمند در مدیریت عواطف و پذیرش تغییرات طبیعی در زندگی است. این رفتار با مفهوم خدمت‌پذیری مطابقت دارد، چرا که فرد با حفظ عزت نفس و مدیریت هیجانات، از حمایت دیگران بهره‌مند می‌شود."
          },
          {
            "aspect": "emotion",
            "subject": "امیدواری",
            "based_on_answer": "و امیدوارم که زندگی بهتری برای آن‌ها فراهم کنم",
            "reasoning": "ابراز امیدواری برای آینده بهتر برای فرزندان نشان‌دهنده احساس مثبت نسبت به آینده و توانایی ایجاد انگیزه برای زندگی است. این موضوع به عنوان یک هیجان سالم شناخته می‌شود که می‌تواند کیفیت زندگی سالمند را بهبود بخشد."
          },
          {
            "aspect": "belief",
            "subject": "توسعه معنای دارایی",
            "based_on_answer": "بله، دو دختری دارم که حمایت می‌کنند",
            "reasoning": "بیان حمایت فرزندان و ارزش‌گذاری بر آن به‌عنوان یک دارایی معنوی نشان‌دهنده جامع‌نگری سالمند به دستاوردهای زندگی و توسعه معنای دارایی است. این باور سالم می‌تواند به افزایش رضایت و کاهش استرس کمک کند."
          }
        ]
      }
    },
    {
      "question_number": 12,
      "question": "وضعیت اقتصادی چطور است؟ آیا شغل مناسبی دارید یا فرزندانتان؟",
      "answer": "وضعیت بسیار بد است. درآمد فرزندانم اسان نیست. اکثراً بیکارند و فشار اقتصادی سختی را متحمل می‌شوند.",
      "analysis": {
        "unhealthy": [
          {
            "aspect": "emotion",
            "subject": "ناامیدی",
            "based_on_answer": "وضعیت بسیار بد است.",
            "reasoning": "بیان وضعیت اقتصادی بسیار بد، نشان‌دهنده احساس ناامیدی نسبت به شرایط موجود است. این احساس می‌تواند منجر به کاهش انگیزه برای مواجهه با مشکلات شود و بر سلامت روان فرد تأثیر منفی بگذارد."
          },
          {
            "aspect": "emotion",
            "subject": "اضطراب و تشویش",
            "based_on_answer": "فشار اقتصادی سختی را متحمل می‌شوند.",
            "reasoning": "توصیف فشار اقتصادی سخت، نشان‌دهنده اضطراب و نگرانی شدید نسبت به وضعیت اقتصادی و آینده است. این نوع هیجان منفی در صورت ادامه‌دار بودن می‌تواند سلامت روان را تحت تأثیر قرار دهد."
          },
          {
            "aspect": "belief",
            "subject": "نگرش منفی و سیاه‌نمایی نسبت به سابقه شغلی",
            "based_on_answer": "اکثراً بیکارند.",
            "reasoning": "بیان بیکاری فرزندان بدون اشاره به تلاش یا امید برای تغییر، می‌تواند نشان‌دهنده نگرش منفی نسبت به وضعیت شغلی و اجتماعی فرزندان باشد که این نگرش ممکن است به کاهش تلاش برای بهبود شرایط منجر شود."
          }
        ],
        "healthy": []
      }
    },
    {
      "question_number": 13,
      "question": "در آخر، اگر بخواهید به جوانان آینده نصیحتی کنید، چه خواهید گفت؟",
      "answer": "جوانان باید تلاش کنند و هرگز ناامید نشوند. ما همه مشکلات خود را با تلاش و زحمت قابل حل می‌دانستیم.",
      "analysis": {
        "unhealthy": [],
        "healthy": [
          {
            "aspect": "emotion",
            "subject": "امیدواری",
            "based_on_answer": "جوانان باید تلاش کنند و هرگز ناامید نشوند.",
            "reasoning": "امیدواری یکی از هیجانات مثبت است که در این پاسخ کاربر به وضوح دیده می‌شود. تاکید بر عدم ناامیدی نشان‌دهنده تنظیم سالم هیجانات و برخورد مثبت با چالش‌ها است."
          },
          {
            "aspect": "belief",
            "subject": "توسعه معنای دارایی",
            "based_on_answer": "ما همه مشکلات خود را با تلاش و زحمت قابل حل می‌دانستیم.",
            "reasoning": "این باور نشان‌دهنده نگاه مثبت و جامع به دارایی‌ها و توانمندی‌های فرد است. باور به اینکه مشکلات با تلاش قابل حل هستند، نشان‌دهنده توسعه معنای دارایی و پذیرش مسئولیت فردی است."
          },
          {
            "aspect": "behavior",
            "subject": "توسعه خود",
            "based_on_answer": "جوانان باید تلاش کنند و هرگز ناامید نشوند.",
            "reasoning": "توصیه به تلاش و پشتکار نشان‌دهنده رفتار سالم و فعالانه در جهت توسعه خود است. این رفتار در سالمندان می‌تواند به حفظ انگیزه و معنا در زندگی کمک کند."
          },
          {
            "aspect": "behavior",
            "subject": "اهتمام ورزی به انتقال تجارب",
            "based_on_answer": "ما همه مشکلات خود را با تلاش و زحمت قابل حل می‌دانستیم.",
            "reasoning": "اشاره به تجربیات گذشته و تلاش برای انتقال این تجربه به نسل جوان نشان‌دهنده اهتمام سالمند به انتقال تجارب است که یک رفتار مثبت و سازنده محسوب می‌شود."
          }
        ]
      }
    }
  ],
  "processing_stats": {
    "total_questions": 13,
    "successful_analyses": 13,
    "failed_analyses": 0,
    "retry_attempts": 4,
    "errors_by_type": {}
  }
}